etherscan_py/__init__.py
etherscan_py/etherscan_py.py
etherscan_py-0.2.3.dist-info/LICENSE
etherscan_py-0.2.3.dist-info/METADATA
etherscan_py-0.2.3.dist-info/WHEEL
etherscan_py-0.2.3.dist-info/top_level.txt
etherscan_py-0.2.3.dist-info/RECORD
