Metadata-Version: 2.1
Name: etherscan-py
Version: 0.2.3
Summary: Powerful Python wrapper over Etherscan API for data collection.
Home-page: https://github.com/juliankoh/etherscan_py
Author: Julian Koh
Author-email: juliankohtx@gmail.com
License: MIT license
Keywords: etherscan_py
Platform: UNKNOWN
Classifier: Development Status :: 2 - Pre-Alpha
Classifier: Intended Audience :: Developers
Classifier: License :: OSI Approved :: MIT License
Classifier: Natural Language :: English
Classifier: Programming Language :: Python :: 3
Classifier: Programming Language :: Python :: 3.5
Classifier: Programming Language :: Python :: 3.6
Classifier: Programming Language :: Python :: 3.7
Classifier: Programming Language :: Python :: 3.8
Requires-Python: >=3.5
